LICENSE
MANIFEST.in
README.rst
setup.py
django_studiogdo.egg-info/PKG-INFO
django_studiogdo.egg-info/SOURCES.txt
django_studiogdo.egg-info/dependency_links.txt
django_studiogdo.egg-info/requires.txt
django_studiogdo.egg-info/top_level.txt
project/__init__.py
project/settings.py
project/urls.py
project/wsgi.py
studiogdo/__init__.py
studiogdo/api.py
studiogdo/apps.py
studiogdo/context_processors.py
studiogdo/middleware.py
studiogdo/urls.py
studiogdo/urls_pip.py
studiogdo/views.py
studiogdo/pip/__init__.py
studiogdo/pip/admin.py
studiogdo/pip/pathresolvers.py
studiogdo/pip/views.py
studiogdo/skel/__init__.py
studiogdo/skel/path.py
studiogdo/skel/renderer.py
studiogdo/skel/tests_path.py
studiogdo/skel/tests_skel_base.py
studiogdo/skel/tests/__init__.py
studiogdo/skel/tests/imprim/__init__.py
studiogdo/skel/tests/imprim/tests_imprim.py
studiogdo/static/studiogdo/js/serializeForm.coffee
studiogdo/static/studiogdo/js/serializeForm.js
studiogdo/static/studiogdo/js/serializeForm.min.js
studiogdo/static/studiogdo/js/skeleton.coffee
studiogdo/static/studiogdo/js/skeleton.js
studiogdo/static/studiogdo/js/skeleton.min.js
studiogdo/static/studiogdo/js/studiogdo.coffee
studiogdo/static/studiogdo/js/studiogdo.js
studiogdo/static/studiogdo/js/studiogdo.min.js
studiogdo/static/studiogdo/js/list/listAndSelection.coffee
studiogdo/static/studiogdo/js/list/listAndSelection.js
studiogdo/static/studiogdo/js/list/listAndSelection.min.js
studiogdo/static/studiogdo/js/list/listCellForm.coffee
studiogdo/static/studiogdo/js/list/listCellForm.js
studiogdo/static/studiogdo/js/list/listCellForm.min.js
studiogdo/static/studiogdo/js/list/listFilter.coffee
studiogdo/static/studiogdo/js/list/listFilter.js
studiogdo/static/studiogdo/js/list/listFilter.map
studiogdo/static/studiogdo/js/list/listFilter.min.js
studiogdo/static/studiogdo/js/list/listOrSelection.coffee
studiogdo/static/studiogdo/js/list/listOrSelection.js
studiogdo/static/studiogdo/js/list/listOrSelection.map
studiogdo/static/studiogdo/js/list/listOrSelection.min.js
studiogdo/static/studiogdo/js/list/listSelectionForm.coffee
studiogdo/static/studiogdo/js/list/listSelectionForm.js
