Metadata-Version: 1.1
Name: django-studiogdo
Version: 0.2.45
Summary: Django implementation of StudioGdo MVC extension.
Home-page: http://www.coworks.pro/
Author: Guillaume Doumenc
Author-email: gdoumenc@coworks.pro
License: BSD License
Platform: UNKNOWN
Classifier: Environment :: Web Environment
Classifier: Framework :: Django
Classifier: Intended Audience :: Developers
Classifier: License :: OSI Approved :: BSD License
Classifier: Operating System :: OS Independent
Classifier: Programming Language :: Python
Classifier: Topic :: Internet :: WWW/HTTP
Classifier: Topic :: Internet :: WWW/HTTP :: Dynamic Content
